covid_19/__init__.py
covid_19/csse_data.py
covid_19/us_tests_cdc.py
covid_19_dryampy-0.3.9.dist-info/LICENSE
covid_19_dryampy-0.3.9.dist-info/METADATA
covid_19_dryampy-0.3.9.dist-info/WHEEL
covid_19_dryampy-0.3.9.dist-info/top_level.txt
covid_19_dryampy-0.3.9.dist-info/RECORD
