Metadata-Version: 2.1
Name: covid-19-dryampy
Version: 0.3.9
Summary: packages used to throw around covid-19 data.
Home-page: https://github.com/DrYampy/covid_19.git
Author: Steven Yampolsky
Author-email: syampols@gmail.com
License: UNKNOWN
Platform: UNKNOWN
Classifier: Programming Language :: Python :: 3
Classifier: License :: OSI Approved :: MIT License
Classifier: Operating System :: OS Independent
Requires-Python: >=3.6
